aminacadea/__init__.py
aminacadea/amina.py
aminacadea-0.0.5.dist-info/LICENSE
aminacadea-0.0.5.dist-info/METADATA
aminacadea-0.0.5.dist-info/WHEEL
aminacadea-0.0.5.dist-info/top_level.txt
aminacadea-0.0.5.dist-info/RECORD
