Metadata-Version: 2.1
Name: aminacadea
Version: 0.0.5
Summary: The Aminacadea library is a helper for tflite-model-maker for use in Google Colab.
Author-email: the3megaguy <mmm111@hotmail.com>
Project-URL: Homepage, https://github.com/mmmwembe/aminacadea
Project-URL: Bug Tracker, https://github.com/mmmwembe/aminacadea/issues
Classifier: Programming Language :: Python :: 3
Classifier: License :: OSI Approved :: MIT License
Classifier: Operating System :: OS Independent
Requires-Python: >=3.7
License-File: LICENSE
Requires-Dist: Pillow (==7.1.*)
Requires-Dist: matplotlib (==3.2.*)
